mcp_data_analyzer_cyj/__init__.py
mcp_data_analyzer_cyj/__main__.py
mcp_data_analyzer_cyj/cli.py
mcp_data_analyzer_cyj/core.py
mcp_data_analyzer_cyj-0.1.2.dist-info/METADATA
mcp_data_analyzer_cyj-0.1.2.dist-info/WHEEL
mcp_data_analyzer_cyj-0.1.2.dist-info/entry_points.txt
mcp_data_analyzer_cyj-0.1.2.dist-info/top_level.txt
mcp_data_analyzer_cyj-0.1.2.dist-info/RECORD
