Metadata-Version: 2.4
Name: mcp-data-analyzer-cyj
Version: 0.1.2
Summary: car sales data analyzer mcp server
Requires-Python: >=3.10
Requires-Dist: mcp[cli]>=1.6.0
Requires-Dist: pandas>=2.2.3
Requires-Dist: seaborn>=0.13.2
Requires-Dist: twine>=6.1.0
Requires-Dist: openpyxl>=3.1.5
